yaetos/__init__.py
yaetos/__version__.py
yaetos/airflow_template.py
yaetos/airflow_template_k8s.py
yaetos/athena.py
yaetos/clickhouse.py
yaetos/daily_incremental_job.py
yaetos/db_utils.py
yaetos/definition.json
yaetos/definition_standalone_cluster.json
yaetos/deploy.py
yaetos/deploy_airflow.py
yaetos/deploy_aws_data_pipeline.py
yaetos/deploy_emr.py
yaetos/deploy_k8s.py
yaetos/deploy_utils.py
yaetos/env_dispatchers.py
yaetos/etl_utils.py
yaetos/excel_utils.py
yaetos/git_utils.py
yaetos/kafka_utils.py
yaetos/launcher.py
yaetos/logger.py
yaetos/mysql_job.py
yaetos/oracle.py
yaetos/oracle_sql_job.py
yaetos/pandas_utils.py
yaetos/redshift_pandas.py
yaetos/redshift_spark.py
yaetos/spark_utils.py
yaetos/sql_pandas_job.py
yaetos/sql_spark_job.py
yaetos/windows_utils.py
yaetos/libs/analysis_toolkit/__init__.py
yaetos/libs/analysis_toolkit/api_helper.py
yaetos/libs/analysis_toolkit/compare_pandas_dfs.py
yaetos/libs/analysis_toolkit/query_helper.py
yaetos/libs/analysis_toolkit/query_pandasql.py
yaetos/libs/analysis_toolkit/query_sparksql_local.py
yaetos/libs/generic_jobs/__init__.py
yaetos/libs/generic_jobs/compare_job.py
yaetos/libs/generic_jobs/copy_job.py
yaetos/libs/generic_jobs/copy_raw_job.py
yaetos/libs/generic_jobs/deployer.py
yaetos/libs/generic_jobs/dummy_job.py
yaetos/libs/generic_jobs/launcher.py
yaetos/libs/generic_jobs/list_files_job.py
yaetos/libs/generic_jobs/sql_pandas_job.py
yaetos/libs/generic_jobs/sql_spark_job.py
yaetos/libs/pytest_utils/__init__.py
yaetos/libs/pytest_utils/conftest.py
yaetos/libs/python_db_connectors/__init__.py
yaetos/libs/python_db_connectors/query_hive.py
yaetos/libs/python_db_connectors/query_mysql.py
yaetos/libs/python_db_connectors/query_oracle.py
yaetos/libs/python_db_connectors/query_redshift.py
yaetos/libs/python_db_connectors/query_salesforce.py
yaetos/scripts/__init__.py
yaetos/scripts/github_pythonapp.yml
yaetos/scripts/requirements_base.txt
yaetos/scripts/requirements_base_alt.txt
yaetos/scripts/requirements_dev.txt
yaetos-0.12.5.dist-info/LICENSE.md
yaetos-0.12.5.dist-info/METADATA
yaetos-0.12.5.dist-info/WHEEL
yaetos-0.12.5.dist-info/entry_points.txt
yaetos-0.12.5.dist-info/top_level.txt
yaetos-0.12.5.dist-info/RECORD
