Metadata-Version: 2.1
Name: yaetos
Version: 0.12.5
Summary: Write data & AI pipelines in (SQL, Spark, Pandas) and deploy them to the cloud, simplified
Home-page: https://github.com/arthurprevot/yaetos
Author: Arthur Prevot
Author-email: arthrprevot@gmail.com
Project-URL: Bug Reports, https://github.com/arthurprevot/yaetos/issues
Project-URL: Source, https://github.com/arthurprevot/yaetos/
Keywords: etl,data pipelines,spark,aws
Classifier: Development Status :: 4 - Beta
Classifier: Intended Audience :: Developers
Classifier: Topic :: Scientific/Engineering
Classifier: License :: OSI Approved :: Apache Software License
Classifier: Programming Language :: Python :: 3
Classifier: Programming Language :: Python :: 3.7
Classifier: Programming Language :: Python :: 3.8
Classifier: Programming Language :: Python :: 3.9
Classifier: Programming Language :: Python :: 3.10
Requires-Python: >=2.7, <4
License-File: LICENSE.md
Requires-Dist: pyyaml
Requires-Dist: awscli
Requires-Dist: boto3
Requires-Dist: cloudpathlib
Requires-Dist: pandas
Requires-Dist: sqlalchemy
Requires-Dist: networkx
Requires-Dist: duckdb
Requires-Dist: py4j
